{
  "game": "bedwars-teams-of-2",
  "timestamp": 1768860901362,
  "entries": [
    {
      "username": "Gaelzkh",
      "value": 16036
    },
    {
      "username": "LordBazoka",
      "value": 16003
    },
    {
      "username": "Sm00th Nitr0",
      "value": 8543
    },
    {
      "username": "luvhasfallen",
      "value": 8423
    },
    {
      "username": "iz1yaD",
      "value": 8376
    },
    {
      "username": "DamDamFTW2000",
      "value": 8025
    },
    {
      "username": "Iqnaciobl4de",
      "value": 7820
    },
    {
      "username": "ZeKreTzZ",
      "value": 7547
    },
    {
      "username": "Luyzinn13",
      "value": 7315
    },
    {
      "username": "qAnung",
      "value": 7135
    },
    {
      "username": "CyberXiao",
      "value": 6544
    },
    {
      "username": "BudgiewQ",
      "value": 5925
    },
    {
      "username": "w3ssimXD",
      "value": 5870
    },
    {
      "username": "AeroAman21",
      "value": 5641
    },
    {
      "username": "GHzinnBRnxt",
      "value": 5088
    },
    {
      "username": "Vaniaurrr",
      "value": 5060
    },
    {
      "username": "JasonH8all",
      "value": 4807
    },
    {
      "username": "killer AWY",
      "value": 4789
    },
    {
      "username": "SLR Mohamed",
      "value": 4715
    },
    {
      "username": "Springy327",
      "value": 4695
    },
    {
      "username": "Vvvxjz",
      "value": 4574
    },
    {
      "username": "TheEpicGlurak27",
      "value": 4552
    },
    {
      "username": "FireGecko6963",
      "value": 4542
    },
    {
      "username": "MrDuck3265YT",
      "value": 4406
    },
    {
      "username": "Plut0H3x",
      "value": 4327
    },
    {
      "username": "kedama1013",
      "value": 4325
    },
    {
      "username": "dupthecow",
      "value": 4311
    },
    {
      "username": "EGYPTvip6",
      "value": 4300
    },
    {
      "username": "kuchenfred15",
      "value": 4068
    },
    {
      "username": "Xylo7 4953",
      "value": 4061
    },
    {
      "username": "op black1201",
      "value": 4002
    },
    {
      "username": "TheKxngCrack",
      "value": 3962
    },
    {
      "username": "MalyMzel",
      "value": 3909
    },
    {
      "username": "Xlzar x 1",
      "value": 3844
    },
    {
      "username": "MKUltra9853",
      "value": 3770
    },
    {
      "username": "physicV9",
      "value": 3754
    },
    {
      "username": "Hamusuke0224",
      "value": 3591
    },
    {
      "username": "iTz1Hamood",
      "value": 3571
    },
    {
      "username": "Chernozhoypi",
      "value": 3503
    },
    {
      "username": "iLoyalzkh",
      "value": 3499
    },
    {
      "username": "crfanth",
      "value": 3285
    },
    {
      "username": "yuhitserica",
      "value": 3261
    },
    {
      "username": "REAL OBAMA3355",
      "value": 3189
    },
    {
      "username": "JafStok",
      "value": 3145
    },
    {
      "username": "Flooping e8",
      "value": 3129
    },
    {
      "username": "Y123y gaming",
      "value": 3091
    },
    {
      "username": "awesome a1fie",
      "value": 3048
    },
    {
      "username": "PizzaYoghurt",
      "value": 3045
    },
    {
      "username": "Bradleyv09",
      "value": 3027
    },
    {
      "username": "THE AUDACITY258",
      "value": 2997
    }
  ]
}